jupyter_shared_docprovider/__init__.py
jupyter_shared_docprovider-0.2.1.data/data/share/jupyter/labextensions/@jupyter/shared-docprovider-extension/package.json
jupyter_shared_docprovider-0.2.1.data/data/share/jupyter/labextensions/@jupyter/shared-docprovider-extension/static/15.76819a5646d28763cc75.js
jupyter_shared_docprovider-0.2.1.data/data/share/jupyter/labextensions/@jupyter/shared-docprovider-extension/static/193.9298585bb344970ac64e.js
jupyter_shared_docprovider-0.2.1.data/data/share/jupyter/labextensions/@jupyter/shared-docprovider-extension/static/193.9298585bb344970ac64e.js.LICENSE.txt
jupyter_shared_docprovider-0.2.1.data/data/share/jupyter/labextensions/@jupyter/shared-docprovider-extension/static/234.d1e66e26b954e7396aa2.js
jupyter_shared_docprovider-0.2.1.data/data/share/jupyter/labextensions/@jupyter/shared-docprovider-extension/static/3.3d5fa3772863bffa9d33.js
jupyter_shared_docprovider-0.2.1.data/data/share/jupyter/labextensions/@jupyter/shared-docprovider-extension/static/516.7e49bc64f7ba3c91745a.js
jupyter_shared_docprovider-0.2.1.data/data/share/jupyter/labextensions/@jupyter/shared-docprovider-extension/static/612.84f1eca6687e3de11269.js
jupyter_shared_docprovider-0.2.1.data/data/share/jupyter/labextensions/@jupyter/shared-docprovider-extension/static/672.e570db7dcb12e93fff63.js
jupyter_shared_docprovider-0.2.1.data/data/share/jupyter/labextensions/@jupyter/shared-docprovider-extension/static/remoteEntry.d646c907a9ae4aecca46.js
jupyter_shared_docprovider-0.2.1.data/data/share/jupyter/labextensions/@jupyter/shared-docprovider-extension/static/style.js
jupyter_shared_docprovider-0.2.1.data/data/share/jupyter/labextensions/@jupyter/shared-docprovider-extension/static/third-party-licenses.json
jupyter_shared_docprovider-0.2.1.data/data/share/jupyter/labextensions/@jupyter/shared-docprovider-extension/install.json
jupyter_shared_docprovider-0.2.1.dist-info/METADATA
jupyter_shared_docprovider-0.2.1.dist-info/WHEEL
jupyter_shared_docprovider-0.2.1.dist-info/licenses/LICENSE
jupyter_shared_docprovider-0.2.1.dist-info/RECORD
